lite_logging/__init__.py
lite_logging/lite_logging.py
lite_logging-1.0.0.dist-info/licenses/LICENSE
lite_logging-1.0.0.dist-info/METADATA
lite_logging-1.0.0.dist-info/WHEEL
lite_logging-1.0.0.dist-info/top_level.txt
lite_logging-1.0.0.dist-info/RECORD
