Metadata-Version: 2.4
Name: lite_logging
Version: 1.0.0
Summary: A library for terminal logging with color support and debug information
Author: Missclick
Author-email: gabrielgarronedev@gmail.com
Classifier: Programming Language :: Python :: 3
Classifier: License :: OSI Approved :: MIT License
Classifier: Operating System :: OS Independent
Requires-Python: >=3.6
License-File: LICENSE
Dynamic: author
Dynamic: author-email
Dynamic: classifier
Dynamic: license-file
Dynamic: requires-python
Dynamic: summary
